[
  {
    "date": "2026-06-01",
    "imsak": "04:53",
    "fajr": "05:03",
    "syuruk": "06:20",
    "dhuhr": "12:32",
    "asr": "15:56",
    "maghrib": "18:36",
    "isha": "19:50"
  },
  {
    "date": "2026-06-02",
    "imsak": "04:53",
    "fajr": "05:03",
    "syuruk": "06:20",
    "dhuhr": "12:32",
    "asr": "15:56",
    "maghrib": "18:36",
    "isha": "19:50"
  },
  {
    "date": "2026-06-03",
    "imsak": "04:53",
    "fajr": "05:03",
    "syuruk": "06:20",
    "dhuhr": "12:32",
    "asr": "15:56",
    "maghrib": "18:36",
    "isha": "19:50"
  },
  {
    "date": "2026-06-04",
    "imsak": "04:53",
    "fajr": "05:03",
    "syuruk": "06:21",
    "dhuhr": "12:32",
    "asr": "15:56",
    "maghrib": "18:36",
    "isha": "19:50"
  },
  {
    "date": "2026-06-05",
    "imsak": "04:53",
    "fajr": "05:03",
    "syuruk": "06:21",
    "dhuhr": "12:32",
    "asr": "15:57",
    "maghrib": "18:37",
    "isha": "19:51"
  },
  {
    "date": "2026-06-06",
    "imsak": "04:53",
    "fajr": "05:03",
    "syuruk": "06:21",
    "dhuhr": "12:32",
    "asr": "15:57",
    "maghrib": "18:37",
    "isha": "19:51"
  },
  {
    "date": "2026-06-07",
    "imsak": "04:53",
    "fajr": "05:03",
    "syuruk": "06:21",
    "dhuhr": "12:33",
    "asr": "15:57",
    "maghrib": "18:37",
    "isha": "19:51"
  },
  {
    "date": "2026-06-08",
    "imsak": "04:53",
    "fajr": "05:03",
    "syuruk": "06:21",
    "dhuhr": "12:33",
    "asr": "15:57",
    "maghrib": "18:37",
    "isha": "19:51"
  },
  {
    "date": "2026-06-09",
    "imsak": "04:53",
    "fajr": "05:03",
    "syuruk": "06:21",
    "dhuhr": "12:33",
    "asr": "15:58",
    "maghrib": "18:37",
    "isha": "19:52"
  },
  {
    "date": "2026-06-10",
    "imsak": "04:54",
    "fajr": "05:04",
    "syuruk": "06:22",
    "dhuhr": "12:33",
    "asr": "15:58",
    "maghrib": "18:38",
    "isha": "19:52"
  },
  {
    "date": "2026-06-11",
    "imsak": "04:54",
    "fajr": "05:04",
    "syuruk": "06:22",
    "dhuhr": "12:33",
    "asr": "15:58",
    "maghrib": "18:38",
    "isha": "19:52"
  },
  {
    "date": "2026-06-12",
    "imsak": "04:54",
    "fajr": "05:04",
    "syuruk": "06:22",
    "dhuhr": "12:34",
    "asr": "15:58",
    "maghrib": "18:38",
    "isha": "19:52"
  },
  {
    "date": "2026-06-13",
    "imsak": "04:54",
    "fajr": "05:04",
    "syuruk": "06:22",
    "dhuhr": "12:34",
    "asr": "15:59",
    "maghrib": "18:38",
    "isha": "19:53"
  },
  {
    "date": "2026-06-14",
    "imsak": "04:54",
    "fajr": "05:04",
    "syuruk": "06:22",
    "dhuhr": "12:34",
    "asr": "15:59",
    "maghrib": "18:38",
    "isha": "19:53"
  },
  {
    "date": "2026-06-15",
    "imsak": "04:54",
    "fajr": "05:04",
    "syuruk": "06:23",
    "dhuhr": "12:34",
    "asr": "15:59",
    "maghrib": "18:39",
    "isha": "19:53"
  },
  {
    "date": "2026-06-16",
    "imsak": "04:55",
    "fajr": "05:05",
    "syuruk": "06:23",
    "dhuhr": "12:34",
    "asr": "15:59",
    "maghrib": "18:39",
    "isha": "19:53"
  },
  {
    "date": "2026-06-17",
    "imsak": "04:55",
    "fajr": "05:05",
    "syuruk": "06:23",
    "dhuhr": "12:35",
    "asr": "16:00",
    "maghrib": "18:39",
    "isha": "19:54"
  },
  {
    "date": "2026-06-18",
    "imsak": "04:55",
    "fajr": "05:05",
    "syuruk": "06:23",
    "dhuhr": "12:35",
    "asr": "16:00",
    "maghrib": "18:39",
    "isha": "19:54"
  },
  {
    "date": "2026-06-19",
    "imsak": "04:55",
    "fajr": "05:05",
    "syuruk": "06:23",
    "dhuhr": "12:35",
    "asr": "16:00",
    "maghrib": "18:40",
    "isha": "19:54"
  },
  {
    "date": "2026-06-20",
    "imsak": "04:55",
    "fajr": "05:05",
    "syuruk": "06:24",
    "dhuhr": "12:35",
    "asr": "16:00",
    "maghrib": "18:40",
    "isha": "19:54"
  },
  {
    "date": "2026-06-21",
    "imsak": "04:56",
    "fajr": "05:06",
    "syuruk": "06:24",
    "dhuhr": "12:35",
    "asr": "16:00",
    "maghrib": "18:40",
    "isha": "19:54"
  },
  {
    "date": "2026-06-22",
    "imsak": "04:56",
    "fajr": "05:06",
    "syuruk": "06:24",
    "dhuhr": "12:36",
    "asr": "16:01",
    "maghrib": "18:40",
    "isha": "19:55"
  },
  {
    "date": "2026-06-23",
    "imsak": "04:56",
    "fajr": "05:06",
    "syuruk": "06:24",
    "dhuhr": "12:36",
    "asr": "16:01",
    "maghrib": "18:40",
    "isha": "19:55"
  },
  {
    "date": "2026-06-24",
    "imsak": "04:56",
    "fajr": "05:06",
    "syuruk": "06:25",
    "dhuhr": "12:36",
    "asr": "16:01",
    "maghrib": "18:41",
    "isha": "19:55"
  },
  {
    "date": "2026-06-25",
    "imsak": "04:57",
    "fajr": "05:07",
    "syuruk": "06:25",
    "dhuhr": "12:36",
    "asr": "16:01",
    "maghrib": "18:41",
    "isha": "19:55"
  },
  {
    "date": "2026-06-26",
    "imsak": "04:57",
    "fajr": "05:07",
    "syuruk": "06:25",
    "dhuhr": "12:37",
    "asr": "16:02",
    "maghrib": "18:41",
    "isha": "19:55"
  },
  {
    "date": "2026-06-27",
    "imsak": "04:57",
    "fajr": "05:07",
    "syuruk": "06:25",
    "dhuhr": "12:37",
    "asr": "16:02",
    "maghrib": "18:41",
    "isha": "19:56"
  },
  {
    "date": "2026-06-28",
    "imsak": "04:57",
    "fajr": "05:07",
    "syuruk": "06:25",
    "dhuhr": "12:37",
    "asr": "16:02",
    "maghrib": "18:41",
    "isha": "19:56"
  },
  {
    "date": "2026-06-29",
    "imsak": "04:57",
    "fajr": "05:07",
    "syuruk": "06:26",
    "dhuhr": "12:37",
    "asr": "16:02",
    "maghrib": "18:42",
    "isha": "19:56"
  },
  {
    "date": "2026-06-30",
    "imsak": "04:58",
    "fajr": "05:08",
    "syuruk": "06:26",
    "dhuhr": "12:37",
    "asr": "16:02",
    "maghrib": "18:42",
    "isha": "19:56"
  }
]
