[
  {
    "date": "2026-05-01",
    "imsak": "04:02",
    "fajr": "04:12",
    "syuruk": "05:51",
    "dhuhr": "13:02",
    "asr": "16:52",
    "maghrib": "20:02",
    "isha": "21:34"
  },
  {
    "date": "2026-05-02",
    "imsak": "04:00",
    "fajr": "04:10",
    "syuruk": "05:50",
    "dhuhr": "13:01",
    "asr": "16:52",
    "maghrib": "20:03",
    "isha": "21:36"
  },
  {
    "date": "2026-05-03",
    "imsak": "03:58",
    "fajr": "04:08",
    "syuruk": "05:48",
    "dhuhr": "13:01",
    "asr": "16:53",
    "maghrib": "20:05",
    "isha": "21:37"
  },
  {
    "date": "2026-05-04",
    "imsak": "03:57",
    "fajr": "04:07",
    "syuruk": "05:47",
    "dhuhr": "13:01",
    "asr": "16:53",
    "maghrib": "20:06",
    "isha": "21:39"
  },
  {
    "date": "2026-05-05",
    "imsak": "03:55",
    "fajr": "04:05",
    "syuruk": "05:46",
    "dhuhr": "13:01",
    "asr": "16:53",
    "maghrib": "20:07",
    "isha": "21:40"
  },
  {
    "date": "2026-05-06",
    "imsak": "03:53",
    "fajr": "04:03",
    "syuruk": "05:45",
    "dhuhr": "13:01",
    "asr": "16:54",
    "maghrib": "20:08",
    "isha": "21:42"
  },
  {
    "date": "2026-05-07",
    "imsak": "03:51",
    "fajr": "04:01",
    "syuruk": "05:43",
    "dhuhr": "13:01",
    "asr": "16:54",
    "maghrib": "20:09",
    "isha": "21:44"
  },
  {
    "date": "2026-05-08",
    "imsak": "03:50",
    "fajr": "04:00",
    "syuruk": "05:42",
    "dhuhr": "13:01",
    "asr": "16:54",
    "maghrib": "20:10",
    "isha": "21:45"
  },
  {
    "date": "2026-05-09",
    "imsak": "03:48",
    "fajr": "03:58",
    "syuruk": "05:41",
    "dhuhr": "13:01",
    "asr": "16:54",
    "maghrib": "20:11",
    "isha": "21:47"
  },
  {
    "date": "2026-05-10",
    "imsak": "03:46",
    "fajr": "03:56",
    "syuruk": "05:40",
    "dhuhr": "13:01",
    "asr": "16:55",
    "maghrib": "20:12",
    "isha": "21:48"
  },
  {
    "date": "2026-05-11",
    "imsak": "03:45",
    "fajr": "03:55",
    "syuruk": "05:39",
    "dhuhr": "13:01",
    "asr": "16:55",
    "maghrib": "20:13",
    "isha": "21:50"
  },
  {
    "date": "2026-05-12",
    "imsak": "03:43",
    "fajr": "03:53",
    "syuruk": "05:38",
    "dhuhr": "13:01",
    "asr": "16:55",
    "maghrib": "20:14",
    "isha": "21:51"
  },
  {
    "date": "2026-05-13",
    "imsak": "03:41",
    "fajr": "03:51",
    "syuruk": "05:37",
    "dhuhr": "13:01",
    "asr": "16:56",
    "maghrib": "20:15",
    "isha": "21:53"
  },
  {
    "date": "2026-05-14",
    "imsak": "03:40",
    "fajr": "03:50",
    "syuruk": "05:36",
    "dhuhr": "13:01",
    "asr": "16:56",
    "maghrib": "20:16",
    "isha": "21:54"
  },
  {
    "date": "2026-05-15",
    "imsak": "03:38",
    "fajr": "03:48",
    "syuruk": "05:35",
    "dhuhr": "13:01",
    "asr": "16:56",
    "maghrib": "20:17",
    "isha": "21:56"
  },
  {
    "date": "2026-05-16",
    "imsak": "03:37",
    "fajr": "03:47",
    "syuruk": "05:34",
    "dhuhr": "13:01",
    "asr": "16:56",
    "maghrib": "20:18",
    "isha": "21:57"
  },
  {
    "date": "2026-05-17",
    "imsak": "03:35",
    "fajr": "03:45",
    "syuruk": "05:33",
    "dhuhr": "13:01",
    "asr": "16:57",
    "maghrib": "20:19",
    "isha": "21:59"
  },
  {
    "date": "2026-05-18",
    "imsak": "03:34",
    "fajr": "03:44",
    "syuruk": "05:32",
    "dhuhr": "13:01",
    "asr": "16:57",
    "maghrib": "20:20",
    "isha": "22:00"
  },
  {
    "date": "2026-05-19",
    "imsak": "03:32",
    "fajr": "03:42",
    "syuruk": "05:31",
    "dhuhr": "13:01",
    "asr": "16:57",
    "maghrib": "20:21",
    "isha": "22:02"
  },
  {
    "date": "2026-05-20",
    "imsak": "03:31",
    "fajr": "03:41",
    "syuruk": "05:30",
    "dhuhr": "13:01",
    "asr": "16:58",
    "maghrib": "20:22",
    "isha": "22:03"
  },
  {
    "date": "2026-05-21",
    "imsak": "03:30",
    "fajr": "03:40",
    "syuruk": "05:29",
    "dhuhr": "13:01",
    "asr": "16:58",
    "maghrib": "20:23",
    "isha": "22:04"
  },
  {
    "date": "2026-05-22",
    "imsak": "03:28",
    "fajr": "03:38",
    "syuruk": "05:29",
    "dhuhr": "13:01",
    "asr": "16:58",
    "maghrib": "20:23",
    "isha": "22:06"
  },
  {
    "date": "2026-05-23",
    "imsak": "03:27",
    "fajr": "03:37",
    "syuruk": "05:28",
    "dhuhr": "13:01",
    "asr": "16:58",
    "maghrib": "20:24",
    "isha": "22:07"
  },
  {
    "date": "2026-05-24",
    "imsak": "03:26",
    "fajr": "03:36",
    "syuruk": "05:27",
    "dhuhr": "13:01",
    "asr": "16:59",
    "maghrib": "20:25",
    "isha": "22:09"
  },
  {
    "date": "2026-05-25",
    "imsak": "03:24",
    "fajr": "03:34",
    "syuruk": "05:27",
    "dhuhr": "13:01",
    "asr": "16:59",
    "maghrib": "20:26",
    "isha": "22:10"
  },
  {
    "date": "2026-05-26",
    "imsak": "03:23",
    "fajr": "03:33",
    "syuruk": "05:26",
    "dhuhr": "13:01",
    "asr": "16:59",
    "maghrib": "20:27",
    "isha": "22:11"
  },
  {
    "date": "2026-05-27",
    "imsak": "03:22",
    "fajr": "03:32",
    "syuruk": "05:25",
    "dhuhr": "13:02",
    "asr": "17:00",
    "maghrib": "20:28",
    "isha": "22:13"
  },
  {
    "date": "2026-05-28",
    "imsak": "03:21",
    "fajr": "03:31",
    "syuruk": "05:25",
    "dhuhr": "13:02",
    "asr": "17:00",
    "maghrib": "20:29",
    "isha": "22:14"
  },
  {
    "date": "2026-05-29",
    "imsak": "03:20",
    "fajr": "03:30",
    "syuruk": "05:24",
    "dhuhr": "13:02",
    "asr": "17:00",
    "maghrib": "20:30",
    "isha": "22:15"
  },
  {
    "date": "2026-05-30",
    "imsak": "03:19",
    "fajr": "03:29",
    "syuruk": "05:24",
    "dhuhr": "13:02",
    "asr": "17:00",
    "maghrib": "20:30",
    "isha": "22:17"
  },
  {
    "date": "2026-05-31",
    "imsak": "03:18",
    "fajr": "03:28",
    "syuruk": "05:23",
    "dhuhr": "13:02",
    "asr": "17:01",
    "maghrib": "20:31",
    "isha": "22:18"
  }
]
