[
  {
    "date": "2026-01-01",
    "imsak": "04:27",
    "fajr": "04:37",
    "syuruk": "05:57",
    "dhuhr": "12:22",
    "asr": "15:48",
    "maghrib": "18:40",
    "isha": "19:56"
  },
  {
    "date": "2026-01-02",
    "imsak": "04:28",
    "fajr": "04:38",
    "syuruk": "05:58",
    "dhuhr": "12:23",
    "asr": "15:49",
    "maghrib": "18:40",
    "isha": "19:56"
  },
  {
    "date": "2026-01-03",
    "imsak": "04:28",
    "fajr": "04:38",
    "syuruk": "05:58",
    "dhuhr": "12:23",
    "asr": "15:49",
    "maghrib": "18:41",
    "isha": "19:57"
  },
  {
    "date": "2026-01-04",
    "imsak": "04:29",
    "fajr": "04:39",
    "syuruk": "05:59",
    "dhuhr": "12:24",
    "asr": "15:49",
    "maghrib": "18:41",
    "isha": "19:57"
  },
  {
    "date": "2026-01-05",
    "imsak": "04:30",
    "fajr": "04:40",
    "syuruk": "06:00",
    "dhuhr": "12:24",
    "asr": "15:50",
    "maghrib": "18:42",
    "isha": "19:57"
  },
  {
    "date": "2026-01-06",
    "imsak": "04:30",
    "fajr": "04:40",
    "syuruk": "06:00",
    "dhuhr": "12:25",
    "asr": "15:50",
    "maghrib": "18:42",
    "isha": "19:58"
  },
  {
    "date": "2026-01-07",
    "imsak": "04:31",
    "fajr": "04:41",
    "syuruk": "06:01",
    "dhuhr": "12:25",
    "asr": "15:50",
    "maghrib": "18:42",
    "isha": "19:58"
  },
  {
    "date": "2026-01-08",
    "imsak": "04:31",
    "fajr": "04:41",
    "syuruk": "06:01",
    "dhuhr": "12:25",
    "asr": "15:50",
    "maghrib": "18:43",
    "isha": "19:58"
  },
  {
    "date": "2026-01-09",
    "imsak": "04:32",
    "fajr": "04:42",
    "syuruk": "06:02",
    "dhuhr": "12:26",
    "asr": "15:51",
    "maghrib": "18:43",
    "isha": "19:58"
  },
  {
    "date": "2026-01-10",
    "imsak": "04:33",
    "fajr": "04:43",
    "syuruk": "06:02",
    "dhuhr": "12:26",
    "asr": "15:51",
    "maghrib": "18:43",
    "isha": "19:59"
  },
  {
    "date": "2026-01-11",
    "imsak": "04:33",
    "fajr": "04:43",
    "syuruk": "06:03",
    "dhuhr": "12:27",
    "asr": "15:51",
    "maghrib": "18:44",
    "isha": "19:59"
  },
  {
    "date": "2026-01-12",
    "imsak": "04:34",
    "fajr": "04:44",
    "syuruk": "06:03",
    "dhuhr": "12:27",
    "asr": "15:51",
    "maghrib": "18:44",
    "isha": "19:59"
  },
  {
    "date": "2026-01-13",
    "imsak": "04:35",
    "fajr": "04:45",
    "syuruk": "06:04",
    "dhuhr": "12:27",
    "asr": "15:51",
    "maghrib": "18:44",
    "isha": "19:59"
  },
  {
    "date": "2026-01-14",
    "imsak": "04:35",
    "fajr": "04:45",
    "syuruk": "06:04",
    "dhuhr": "12:28",
    "asr": "15:52",
    "maghrib": "18:44",
    "isha": "19:59"
  },
  {
    "date": "2026-01-15",
    "imsak": "04:36",
    "fajr": "04:46",
    "syuruk": "06:05",
    "dhuhr": "12:28",
    "asr": "15:52",
    "maghrib": "18:45",
    "isha": "19:59"
  },
  {
    "date": "2026-01-16",
    "imsak": "04:36",
    "fajr": "04:46",
    "syuruk": "06:05",
    "dhuhr": "12:28",
    "asr": "15:52",
    "maghrib": "18:45",
    "isha": "19:59"
  },
  {
    "date": "2026-01-17",
    "imsak": "04:37",
    "fajr": "04:47",
    "syuruk": "06:06",
    "dhuhr": "12:29",
    "asr": "15:52",
    "maghrib": "18:45",
    "isha": "20:00"
  },
  {
    "date": "2026-01-18",
    "imsak": "04:38",
    "fajr": "04:48",
    "syuruk": "06:06",
    "dhuhr": "12:29",
    "asr": "15:52",
    "maghrib": "18:45",
    "isha": "20:00"
  },
  {
    "date": "2026-01-19",
    "imsak": "04:38",
    "fajr": "04:48",
    "syuruk": "06:07",
    "dhuhr": "12:29",
    "asr": "15:52",
    "maghrib": "18:45",
    "isha": "20:00"
  },
  {
    "date": "2026-01-20",
    "imsak": "04:39",
    "fajr": "04:49",
    "syuruk": "06:07",
    "dhuhr": "12:30",
    "asr": "15:52",
    "maghrib": "18:45",
    "isha": "20:00"
  },
  {
    "date": "2026-01-21",
    "imsak": "04:39",
    "fajr": "04:49",
    "syuruk": "06:07",
    "dhuhr": "12:30",
    "asr": "15:52",
    "maghrib": "18:46",
    "isha": "20:00"
  },
  {
    "date": "2026-01-22",
    "imsak": "04:40",
    "fajr": "04:50",
    "syuruk": "06:08",
    "dhuhr": "12:30",
    "asr": "15:52",
    "maghrib": "18:46",
    "isha": "20:00"
  },
  {
    "date": "2026-01-23",
    "imsak": "04:40",
    "fajr": "04:50",
    "syuruk": "06:08",
    "dhuhr": "12:31",
    "asr": "15:52",
    "maghrib": "18:46",
    "isha": "20:00"
  },
  {
    "date": "2026-01-24",
    "imsak": "04:41",
    "fajr": "04:51",
    "syuruk": "06:09",
    "dhuhr": "12:31",
    "asr": "15:52",
    "maghrib": "18:46",
    "isha": "20:00"
  },
  {
    "date": "2026-01-25",
    "imsak": "04:42",
    "fajr": "04:52",
    "syuruk": "06:09",
    "dhuhr": "12:31",
    "asr": "15:52",
    "maghrib": "18:46",
    "isha": "20:00"
  },
  {
    "date": "2026-01-26",
    "imsak": "04:42",
    "fajr": "04:52",
    "syuruk": "06:10",
    "dhuhr": "12:31",
    "asr": "15:52",
    "maghrib": "18:46",
    "isha": "20:00"
  },
  {
    "date": "2026-01-27",
    "imsak": "04:43",
    "fajr": "04:53",
    "syuruk": "06:10",
    "dhuhr": "12:32",
    "asr": "15:51",
    "maghrib": "18:46",
    "isha": "19:59"
  },
  {
    "date": "2026-01-28",
    "imsak": "04:43",
    "fajr": "04:53",
    "syuruk": "06:10",
    "dhuhr": "12:32",
    "asr": "15:51",
    "maghrib": "18:46",
    "isha": "19:59"
  },
  {
    "date": "2026-01-29",
    "imsak": "04:44",
    "fajr": "04:54",
    "syuruk": "06:11",
    "dhuhr": "12:32",
    "asr": "15:51",
    "maghrib": "18:46",
    "isha": "19:59"
  },
  {
    "date": "2026-01-30",
    "imsak": "04:44",
    "fajr": "04:54",
    "syuruk": "06:11",
    "dhuhr": "12:32",
    "asr": "15:51",
    "maghrib": "18:46",
    "isha": "19:59"
  },
  {
    "date": "2026-01-31",
    "imsak": "04:45",
    "fajr": "04:55",
    "syuruk": "06:11",
    "dhuhr": "12:32",
    "asr": "15:50",
    "maghrib": "18:46",
    "isha": "19:59"
  }
]
