[
  {
    "date": "2026-06-01",
    "imsak": "04:59",
    "fajr": "05:09",
    "syuruk": "06:26",
    "dhuhr": "12:23",
    "asr": "15:43",
    "maghrib": "18:13",
    "isha": "19:27"
  },
  {
    "date": "2026-06-02",
    "imsak": "04:59",
    "fajr": "05:09",
    "syuruk": "06:26",
    "dhuhr": "12:23",
    "asr": "15:43",
    "maghrib": "18:13",
    "isha": "19:27"
  },
  {
    "date": "2026-06-03",
    "imsak": "04:59",
    "fajr": "05:09",
    "syuruk": "06:27",
    "dhuhr": "12:23",
    "asr": "15:43",
    "maghrib": "18:13",
    "isha": "19:27"
  },
  {
    "date": "2026-06-04",
    "imsak": "04:59",
    "fajr": "05:09",
    "syuruk": "06:27",
    "dhuhr": "12:23",
    "asr": "15:43",
    "maghrib": "18:13",
    "isha": "19:27"
  },
  {
    "date": "2026-06-05",
    "imsak": "05:00",
    "fajr": "05:10",
    "syuruk": "06:27",
    "dhuhr": "12:24",
    "asr": "15:43",
    "maghrib": "18:13",
    "isha": "19:27"
  },
  {
    "date": "2026-06-06",
    "imsak": "05:00",
    "fajr": "05:10",
    "syuruk": "06:27",
    "dhuhr": "12:24",
    "asr": "15:43",
    "maghrib": "18:13",
    "isha": "19:27"
  },
  {
    "date": "2026-06-07",
    "imsak": "05:00",
    "fajr": "05:10",
    "syuruk": "06:28",
    "dhuhr": "12:24",
    "asr": "15:43",
    "maghrib": "18:13",
    "isha": "19:27"
  },
  {
    "date": "2026-06-08",
    "imsak": "05:00",
    "fajr": "05:10",
    "syuruk": "06:28",
    "dhuhr": "12:24",
    "asr": "15:44",
    "maghrib": "18:13",
    "isha": "19:28"
  },
  {
    "date": "2026-06-09",
    "imsak": "05:00",
    "fajr": "05:10",
    "syuruk": "06:28",
    "dhuhr": "12:24",
    "asr": "15:44",
    "maghrib": "18:14",
    "isha": "19:28"
  },
  {
    "date": "2026-06-10",
    "imsak": "05:01",
    "fajr": "05:11",
    "syuruk": "06:28",
    "dhuhr": "12:25",
    "asr": "15:44",
    "maghrib": "18:14",
    "isha": "19:28"
  },
  {
    "date": "2026-06-11",
    "imsak": "05:01",
    "fajr": "05:11",
    "syuruk": "06:29",
    "dhuhr": "12:25",
    "asr": "15:44",
    "maghrib": "18:14",
    "isha": "19:28"
  },
  {
    "date": "2026-06-12",
    "imsak": "05:01",
    "fajr": "05:11",
    "syuruk": "06:29",
    "dhuhr": "12:25",
    "asr": "15:44",
    "maghrib": "18:14",
    "isha": "19:28"
  },
  {
    "date": "2026-06-13",
    "imsak": "05:01",
    "fajr": "05:11",
    "syuruk": "06:29",
    "dhuhr": "12:25",
    "asr": "15:44",
    "maghrib": "18:14",
    "isha": "19:29"
  },
  {
    "date": "2026-06-14",
    "imsak": "05:01",
    "fajr": "05:11",
    "syuruk": "06:29",
    "dhuhr": "12:25",
    "asr": "15:45",
    "maghrib": "18:14",
    "isha": "19:29"
  },
  {
    "date": "2026-06-15",
    "imsak": "05:02",
    "fajr": "05:12",
    "syuruk": "06:30",
    "dhuhr": "12:26",
    "asr": "15:45",
    "maghrib": "18:15",
    "isha": "19:29"
  },
  {
    "date": "2026-06-16",
    "imsak": "05:02",
    "fajr": "05:12",
    "syuruk": "06:30",
    "dhuhr": "12:26",
    "asr": "15:45",
    "maghrib": "18:15",
    "isha": "19:29"
  },
  {
    "date": "2026-06-17",
    "imsak": "05:02",
    "fajr": "05:12",
    "syuruk": "06:30",
    "dhuhr": "12:26",
    "asr": "15:45",
    "maghrib": "18:15",
    "isha": "19:29"
  },
  {
    "date": "2026-06-18",
    "imsak": "05:02",
    "fajr": "05:12",
    "syuruk": "06:30",
    "dhuhr": "12:26",
    "asr": "15:45",
    "maghrib": "18:15",
    "isha": "19:30"
  },
  {
    "date": "2026-06-19",
    "imsak": "05:02",
    "fajr": "05:12",
    "syuruk": "06:31",
    "dhuhr": "12:27",
    "asr": "15:46",
    "maghrib": "18:15",
    "isha": "19:30"
  },
  {
    "date": "2026-06-20",
    "imsak": "05:03",
    "fajr": "05:13",
    "syuruk": "06:31",
    "dhuhr": "12:27",
    "asr": "15:46",
    "maghrib": "18:16",
    "isha": "19:30"
  },
  {
    "date": "2026-06-21",
    "imsak": "05:03",
    "fajr": "05:13",
    "syuruk": "06:31",
    "dhuhr": "12:27",
    "asr": "15:46",
    "maghrib": "18:16",
    "isha": "19:30"
  },
  {
    "date": "2026-06-22",
    "imsak": "05:03",
    "fajr": "05:13",
    "syuruk": "06:31",
    "dhuhr": "12:27",
    "asr": "15:46",
    "maghrib": "18:16",
    "isha": "19:31"
  },
  {
    "date": "2026-06-23",
    "imsak": "05:03",
    "fajr": "05:13",
    "syuruk": "06:32",
    "dhuhr": "12:27",
    "asr": "15:47",
    "maghrib": "18:16",
    "isha": "19:31"
  },
  {
    "date": "2026-06-24",
    "imsak": "05:04",
    "fajr": "05:14",
    "syuruk": "06:32",
    "dhuhr": "12:28",
    "asr": "15:47",
    "maghrib": "18:17",
    "isha": "19:31"
  },
  {
    "date": "2026-06-25",
    "imsak": "05:04",
    "fajr": "05:14",
    "syuruk": "06:32",
    "dhuhr": "12:28",
    "asr": "15:47",
    "maghrib": "18:17",
    "isha": "19:31"
  },
  {
    "date": "2026-06-26",
    "imsak": "05:04",
    "fajr": "05:14",
    "syuruk": "06:32",
    "dhuhr": "12:28",
    "asr": "15:47",
    "maghrib": "18:17",
    "isha": "19:31"
  },
  {
    "date": "2026-06-27",
    "imsak": "05:04",
    "fajr": "05:14",
    "syuruk": "06:32",
    "dhuhr": "12:28",
    "asr": "15:47",
    "maghrib": "18:17",
    "isha": "19:32"
  },
  {
    "date": "2026-06-28",
    "imsak": "05:04",
    "fajr": "05:14",
    "syuruk": "06:32",
    "dhuhr": "12:28",
    "asr": "15:48",
    "maghrib": "18:17",
    "isha": "19:32"
  },
  {
    "date": "2026-06-29",
    "imsak": "05:05",
    "fajr": "05:15",
    "syuruk": "06:33",
    "dhuhr": "12:29",
    "asr": "15:48",
    "maghrib": "18:18",
    "isha": "19:32"
  },
  {
    "date": "2026-06-30",
    "imsak": "05:05",
    "fajr": "05:15",
    "syuruk": "06:33",
    "dhuhr": "12:29",
    "asr": "15:48",
    "maghrib": "18:18",
    "isha": "19:32"
  }
]
